[{"data_hora": "2024-10-11 11:26:15", "mac_address": "10f60a853495", "cpu_porcentagem": 6.6, "ram_porcentagem": 89.2}, {"data_hora": "2024-10-11 11:26:18", "mac_address": "10f60a853495", "cpu_porcentagem": 5.0, "ram_porcentagem": 89.0}, {"data_hora": "2024-10-11 11:26:20", "mac_address": "10f60a853495", "cpu_porcentagem": 9.8, "ram_porcentagem": 88.2}, {"data_hora": "2024-10-11 11:26:22", "mac_address": "10f60a853495", "cpu_porcentagem": 12.3, "ram_porcentagem": 89.6}, {"data_hora": "2024-10-11 11:26:24", "mac_address": "10f60a853495", "cpu_porcentagem": 8.6, "ram_porcentagem": 90.0}, {"data_hora": "2024-10-11 11:26:27", "mac_address": "10f60a853495", "cpu_porcentagem": 7.3, "ram_porcentagem": 90.0}, {"data_hora": "2024-10-11 11:26:29", "mac_address": "10f60a853495", "cpu_porcentagem": 7.6, "ram_porcentagem": 90.3}, {"data_hora": "2024-10-11 11:26:31", "mac_address": "10f60a853495", "cpu_porcentagem": 3.0, "ram_porcentagem": 90.8}, {"data_hora": "2024-10-11 11:26:34", "mac_address": "10f60a853495", "cpu_porcentagem": 3.4, "ram_porcentagem": 90.7}, {"data_hora": "2024-10-11 11:26:36", "mac_address": "10f60a853495", "cpu_porcentagem": 2.5, "ram_porcentagem": 90.8}]